__init__.py
fluffypancakes/__init__.py
fluffypancakes/features.py
fluffypancakes/fluffypancakes.py
fluffypancakes/handler.py
fluffypancakes/recurrent.py
fluffypancakes/data/dataset.csv
fluffypancakes/data/edu_domains.txt
fluffypancakes/data/shortening_services.txt
fluffypancakes/data/ssl_list.txt
fluffypancakes/dependencies/linux/chromedriver
fluffypancakes/dependencies/macOS/chromedriver
fluffypancakes/dependencies/windows/chromedriver.exe
fluffypancakes-0.1.5.dist-info/LICENSE.txt
fluffypancakes-0.1.5.dist-info/METADATA
fluffypancakes-0.1.5.dist-info/WHEEL
fluffypancakes-0.1.5.dist-info/top_level.txt
fluffypancakes-0.1.5.dist-info/RECORD
