Metadata-Version: 2.1
Name: fluffypancakes
Version: 0.1.5
Summary: Detect Phishing Websites using Machine Learning
Home-page: https://github.com/suhasrsharma/FluffyPancakes
Author: Suhas Sharma
Author-email: le.bon.garconn@gmail.com
License: UNKNOWN
Keywords: web-phishing-detection machine-learning
Platform: UNKNOWN
Classifier: Development Status :: 4 - Beta
Classifier: Intended Audience :: Developers
Classifier: Intended Audience :: Education
Classifier: License :: OSI Approved :: MIT License
Classifier: Operating System :: OS Independent
Classifier: Programming Language :: Python :: 2.7
Classifier: Programming Language :: Python :: 3
Classifier: Programming Language :: Python :: 3.6
Classifier: Programming Language :: Python :: 3.7
Requires-Dist: beautifulsoup4 (>=4.9.0)
Requires-Dist: bs4 (>=0.0.1)
Requires-Dist: numpy (>=1.18.2)
Requires-Dist: pandas (>=1.0.4)
Requires-Dist: python-whois (>=0.7.2)
Requires-Dist: requests (>=2.23.0)
Requires-Dist: scikit-learn (>=0.21.3)
Requires-Dist: selenium (>=3.141.0)
Requires-Dist: sklearn (>=0.0)
Requires-Dist: tqdm (>=4.46.0)
Requires-Dist: urllib3 (>=1.25.8)
Provides-Extra: dev
Requires-Dist: pytest (>=3.7) ; extra == 'dev'
Requires-Dist: twine (>=3.1.1) ; extra == 'dev'
